
<LEAInfos xmlns="http://www.sifassociation.org/datamodel/na/4.x">
  <LEAInfo RefId="">
    <LocalId/>
    <LocalIdSystem/>
    <StateProvinceId/>
    <NCESId/>
    <LEAName/>
    <LEAURL/>
    <SchoolDesignationList>
      <SchoolDesignation Codeset=""/>
      <SchoolDesignation Codeset=""/>
    </SchoolDesignationList>
    <EducationAgencyType>
      <Code Codeset=""/>
      <OtherCodeList>
        <OtherCode Codeset=""/>
        <OtherCode Codeset=""/>
      </OtherCodeList>
    </EducationAgencyType>
    <LEAContactList>
      <LEAContact>
        <PublishInDirectory Codeset=""/>
        <ContactInfo>
          <Name Type="">
            <Prefix/>
            <LastName/>
            <FirstName/>
            <MiddleName/>
            <Suffix/>
            <PreferredName/>
            <SortName/>
            <FullName/>
          </Name>
          <PositionTitle/>
          <Role/>
          <Address Type="" TypeCodeset="">
            <Street>
              <Line1/>
              <Line2/>
              <Line3/>
              <Complex/>
              <StreetNumber/>
              <StreetPrefix/>
              <StreetName/>
              <StreetType/>
              <StreetSuffix/>
              <ApartmentType/>
              <ApartmentNumberPrefix/>
              <ApartmentNumber/>
              <ApartmentNumberSuffix/>
            </Street>
            <City/>
            <County/>
            <StateProvince Codeset=""/>
            <StateANSICode Codeset=""/>
            <Country Codeset=""/>
            <PostalCode/>
            <GridLocation>
              <Latitude/>
              <Longitude/>
            </GridLocation>
            <AddressRefId/>
          </Address>
          <AddressRefId/>
          <EmailList>
            <Email SIF_Action="" Type="" TypeCodeset=""/>
            <Email SIF_Action="" Type="" TypeCodeset=""/>
          </EmailList>
          <PhoneNumberList>
            <PhoneNumber SIF_Action="" Type="" TypeCodeset="">
              <Number/>
              <Extension/>
              <ListedStatus/>
            </PhoneNumber>
            <PhoneNumber SIF_Action="" Type="" TypeCodeset="">
              <Number/>
              <Extension/>
              <ListedStatus/>
            </PhoneNumber>
          </PhoneNumberList>
        </ContactInfo>
      </LEAContact>
      <LEAContact>
        <PublishInDirectory Codeset=""/>
        <ContactInfo>
          <Name Type="">
            <Prefix/>
            <LastName/>
            <FirstName/>
            <MiddleName/>
            <Suffix/>
            <PreferredName/>
            <SortName/>
            <FullName/>
          </Name>
          <PositionTitle/>
          <Role/>
          <Address Type="" TypeCodeset="">
            <Street>
              <Line1/>
              <Line2/>
              <Line3/>
              <Complex/>
              <StreetNumber/>
              <StreetPrefix/>
              <StreetName/>
              <StreetType/>
              <StreetSuffix/>
              <ApartmentType/>
              <ApartmentNumberPrefix/>
              <ApartmentNumber/>
              <ApartmentNumberSuffix/>
            </Street>
            <City/>
            <County/>
            <StateProvince Codeset=""/>
            <StateANSICode Codeset=""/>
            <Country Codeset=""/>
            <PostalCode/>
            <GridLocation>
              <Latitude/>
              <Longitude/>
            </GridLocation>
            <AddressRefId/>
          </Address>
          <AddressRefId/>
          <EmailList>
            <Email SIF_Action="" Type="" TypeCodeset=""/>
            <Email SIF_Action="" Type="" TypeCodeset=""/>
          </EmailList>
          <PhoneNumberList>
            <PhoneNumber SIF_Action="" Type="" TypeCodeset="">
              <Number/>
              <Extension/>
              <ListedStatus/>
            </PhoneNumber>
            <PhoneNumber SIF_Action="" Type="" TypeCodeset="">
              <Number/>
              <Extension/>
              <ListedStatus/>
            </PhoneNumber>
          </PhoneNumberList>
        </ContactInfo>
      </LEAContact>
    </LEAContactList>
    <PhoneNumberList>
      <PhoneNumber SIF_Action="" Type="" TypeCodeset="">
        <Number/>
        <Extension/>
        <ListedStatus/>
      </PhoneNumber>
      <PhoneNumber SIF_Action="" Type="" TypeCodeset="">
        <Number/>
        <Extension/>
        <ListedStatus/>
      </PhoneNumber>
    </PhoneNumberList>
    <AddressList>
      <Address SIF_Action="" Type="" TypeCodeset="">
        <Street>
          <Line1/>
          <Line2/>
          <Line3/>
          <Complex/>
          <StreetNumber/>
          <StreetPrefix/>
          <StreetName/>
          <StreetType/>
          <StreetSuffix/>
          <ApartmentType/>
          <ApartmentNumberPrefix/>
          <ApartmentNumber/>
          <ApartmentNumberSuffix/>
        </Street>
        <City/>
        <County/>
        <StateProvince Codeset=""/>
        <StateANSICode Codeset=""/>
        <Country Codeset=""/>
        <PostalCode/>
        <GridLocation>
          <Latitude/>
          <Longitude/>
        </GridLocation>
        <AddressRefId/>
      </Address>
      <Address SIF_Action="" Type="" TypeCodeset="">
        <Street>
          <Line1/>
          <Line2/>
          <Line3/>
          <Complex/>
          <StreetNumber/>
          <StreetPrefix/>
          <StreetName/>
          <StreetType/>
          <StreetSuffix/>
          <ApartmentType/>
          <ApartmentNumberPrefix/>
          <ApartmentNumber/>
          <ApartmentNumberSuffix/>
        </Street>
        <City/>
        <County/>
        <StateProvince Codeset=""/>
        <StateANSICode Codeset=""/>
        <Country Codeset=""/>
        <PostalCode/>
        <GridLocation>
          <Latitude/>
          <Longitude/>
        </GridLocation>
        <AddressRefId/>
      </Address>
    </AddressList>
    <AddressRefIdList>
      <AddressRefId AddressRole=""/>
      <AddressRefId AddressRole=""/>
    </AddressRefIdList>
    <IdentificationInfoList>
      <IdentificationInfo Code="" CodeCodeset=""/>
      <IdentificationInfo Code="" CodeCodeset=""/>
    </IdentificationInfoList>
    <GradeLevels>
      <GradeLevel>
        <Code Codeset=""/>
        <OtherCodeList>
          <OtherCode Codeset=""/>
          <OtherCode Codeset=""/>
        </OtherCodeList>
      </GradeLevel>
      <GradeLevel>
        <Code Codeset=""/>
        <OtherCodeList>
          <OtherCode Codeset=""/>
          <OtherCode Codeset=""/>
        </OtherCodeList>
      </GradeLevel>
    </GradeLevels>
    <OperationalStatus Codeset=""/>
    <OperationalStatusDate/>
    <CongressionalDistrict/>
    <RegionOrganizationList>
      <RegionOrganization>
        <Indicator/>
        <Type/>
      </RegionOrganization>
      <RegionOrganization>
        <Indicator/>
        <Type/>
      </RegionOrganization>
    </RegionOrganizationList>
    <TitleIProgramType Codeset=""/>
    <TitleIIILanguageInstructionProgramType Codeset=""/>
    <SIF_Metadata>
      <TimeElements>
        <TimeElement>
          <Type/>
          <Code/>
          <Name/>
          <Value/>
          <StartDateTime/>
          <EndDateTime/>
          <SpanGaps>
            <SpanGap>
              <Type/>
              <Code/>
              <Name/>
              <Value/>
              <StartDateTime/>
              <EndDateTime/>
            </SpanGap>
            <SpanGap>
              <Type/>
              <Code/>
              <Name/>
              <Value/>
              <StartDateTime/>
              <EndDateTime/>
            </SpanGap>
          </SpanGaps>
          <IsCurrent/>
        </TimeElement>
        <TimeElement>
          <Type/>
          <Code/>
          <Name/>
          <Value/>
          <StartDateTime/>
          <EndDateTime/>
          <SpanGaps>
            <SpanGap>
              <Type/>
              <Code/>
              <Name/>
              <Value/>
              <StartDateTime/>
              <EndDateTime/>
            </SpanGap>
            <SpanGap>
              <Type/>
              <Code/>
              <Name/>
              <Value/>
              <StartDateTime/>
              <EndDateTime/>
            </SpanGap>
          </SpanGaps>
          <IsCurrent/>
        </TimeElement>
      </TimeElements>
      <LifeCycle>
        <Created>
          <DateTime/>
          <Creators>
            <Creator>
              <Name/>
              <ID/>
            </Creator>
            <Creator>
              <Name/>
              <ID/>
            </Creator>
          </Creators>
        </Created>
        <ModificationHistory>
          <Modified>
            <By/>
            <DateTime/>
            <Description/>
          </Modified>
          <Modified>
            <By/>
            <DateTime/>
            <Description/>
          </Modified>
        </ModificationHistory>
        <TimeElements>
          <TimeElement>
            <Type/>
            <Code/>
            <Name/>
            <Value/>
            <StartDateTime/>
            <EndDateTime/>
            <SpanGaps>
              <SpanGap>
                <Type/>
                <Code/>
                <Name/>
                <Value/>
                <StartDateTime/>
                <EndDateTime/>
              </SpanGap>
              <SpanGap>
                <Type/>
                <Code/>
                <Name/>
                <Value/>
                <StartDateTime/>
                <EndDateTime/>
              </SpanGap>
            </SpanGaps>
            <IsCurrent/>
          </TimeElement>
          <TimeElement>
            <Type/>
            <Code/>
            <Name/>
            <Value/>
            <StartDateTime/>
            <EndDateTime/>
            <SpanGaps>
              <SpanGap>
                <Type/>
                <Code/>
                <Name/>
                <Value/>
                <StartDateTime/>
                <EndDateTime/>
              </SpanGap>
              <SpanGap>
                <Type/>
                <Code/>
                <Name/>
                <Value/>
                <StartDateTime/>
                <EndDateTime/>
              </SpanGap>
            </SpanGaps>
            <IsCurrent/>
          </TimeElement>
        </TimeElements>
      </LifeCycle>
      <RightsElements>
        <RightsElement>
          <Cost/>
          <FeesForUse>
            <FeeForUse>
              <UseType/>
              <MeteringType/>
              <MeteringURL/>
              <PerUseCharge Currency="" CurrencyCodeset=""/>
            </FeeForUse>
            <FeeForUse>
              <UseType/>
              <MeteringType/>
              <MeteringURL/>
              <PerUseCharge Currency="" CurrencyCodeset=""/>
            </FeeForUse>
          </FeesForUse>
          <CopyrightStatement/>
          <TermsOfUse/>
        </RightsElement>
        <RightsElement>
          <Cost/>
          <FeesForUse>
            <FeeForUse>
              <UseType/>
              <MeteringType/>
              <MeteringURL/>
              <PerUseCharge Currency="" CurrencyCodeset=""/>
            </FeeForUse>
            <FeeForUse>
              <UseType/>
              <MeteringType/>
              <MeteringURL/>
              <PerUseCharge Currency="" CurrencyCodeset=""/>
            </FeeForUse>
          </FeesForUse>
          <CopyrightStatement/>
          <TermsOfUse/>
        </RightsElement>
      </RightsElements>
      <EducationFilter>
        <MediaTypes>
          <MediaType/>
          <MediaType/>
        </MediaTypes>
        <GradeLevels>
          <GradeLevel>
            <Code Codeset=""/>
            <OtherCodeList>
              <OtherCode Codeset=""/>
              <OtherCode Codeset=""/>
            </OtherCodeList>
          </GradeLevel>
          <GradeLevel>
            <Code Codeset=""/>
            <OtherCodeList>
              <OtherCode Codeset=""/>
              <OtherCode Codeset=""/>
            </OtherCodeList>
          </GradeLevel>
        </GradeLevels>
        <SubjectAreas>
          <SubjectArea>
            <Code Codeset=""/>
            <OtherCodeList>
              <OtherCode Codeset=""/>
              <OtherCode Codeset=""/>
            </OtherCodeList>
          </SubjectArea>
          <SubjectArea>
            <Code Codeset=""/>
            <OtherCodeList>
              <OtherCode Codeset=""/>
              <OtherCode Codeset=""/>
            </OtherCodeList>
          </SubjectArea>
        </SubjectAreas>
        <InterestLevels>
          <InterestLevel>
            <Code Codeset=""/>
            <OtherCodeList>
              <OtherCode Codeset=""/>
              <OtherCode Codeset=""/>
            </OtherCodeList>
          </InterestLevel>
          <InterestLevel>
            <Code Codeset=""/>
            <OtherCodeList>
              <OtherCode Codeset=""/>
              <OtherCode Codeset=""/>
            </OtherCodeList>
          </InterestLevel>
        </InterestLevels>
        <LearningStandardItems>
          <LearningStandardItemRefId/>
          <LearningStandardItemRefId/>
        </LearningStandardItems>
        <BloomsTaxonomyLevels>
          <BloomsTaxonomyLevel Codeset=""/>
          <BloomsTaxonomyLevel Codeset=""/>
        </BloomsTaxonomyLevels>
        <MultipleIntelligences>
          <MultipleIntelligence Codeset=""/>
          <MultipleIntelligence Codeset=""/>
        </MultipleIntelligences>
        <InstructionalStrategies>
          <InstructionalStrategy Codeset=""/>
          <InstructionalStrategy Codeset=""/>
        </InstructionalStrategies>
        <Title/>
        <Summary/>
        <LearningObjectives>
          <LearningObjective/>
          <LearningObjective/>
        </LearningObjectives>
        <ResourceTypes>
          <ResourceType Codeset=""/>
          <ResourceType Codeset=""/>
        </ResourceTypes>
      </EducationFilter>
    </SIF_Metadata>
    <SIF_ExtendedElements>
      <SIF_ExtendedElement Name="" SIF_Action=""/>
      <SIF_ExtendedElement Name="" SIF_Action=""/>
    </SIF_ExtendedElements>
  </LEAInfo>
  <LEAInfo RefId="">
    <LocalId/>
    <LocalIdSystem/>
    <StateProvinceId/>
    <NCESId/>
    <LEAName/>
    <LEAURL/>
    <SchoolDesignationList>
      <SchoolDesignation Codeset=""/>
      <SchoolDesignation Codeset=""/>
    </SchoolDesignationList>
    <EducationAgencyType>
      <Code Codeset=""/>
      <OtherCodeList>
        <OtherCode Codeset=""/>
        <OtherCode Codeset=""/>
      </OtherCodeList>
    </EducationAgencyType>
    <LEAContactList>
      <LEAContact>
        <PublishInDirectory Codeset=""/>
        <ContactInfo>
          <Name Type="">
            <Prefix/>
            <LastName/>
            <FirstName/>
            <MiddleName/>
            <Suffix/>
            <PreferredName/>
            <SortName/>
            <FullName/>
          </Name>
          <PositionTitle/>
          <Role/>
          <Address Type="" TypeCodeset="">
            <Street>
              <Line1/>
              <Line2/>
              <Line3/>
              <Complex/>
              <StreetNumber/>
              <StreetPrefix/>
              <StreetName/>
              <StreetType/>
              <StreetSuffix/>
              <ApartmentType/>
              <ApartmentNumberPrefix/>
              <ApartmentNumber/>
              <ApartmentNumberSuffix/>
            </Street>
            <City/>
            <County/>
            <StateProvince Codeset=""/>
            <StateANSICode Codeset=""/>
            <Country Codeset=""/>
            <PostalCode/>
            <GridLocation>
              <Latitude/>
              <Longitude/>
            </GridLocation>
            <AddressRefId/>
          </Address>
          <AddressRefId/>
          <EmailList>
            <Email SIF_Action="" Type="" TypeCodeset=""/>
            <Email SIF_Action="" Type="" TypeCodeset=""/>
          </EmailList>
          <PhoneNumberList>
            <PhoneNumber SIF_Action="" Type="" TypeCodeset="">
              <Number/>
              <Extension/>
              <ListedStatus/>
            </PhoneNumber>
            <PhoneNumber SIF_Action="" Type="" TypeCodeset="">
              <Number/>
              <Extension/>
              <ListedStatus/>
            </PhoneNumber>
          </PhoneNumberList>
        </ContactInfo>
      </LEAContact>
      <LEAContact>
        <PublishInDirectory Codeset=""/>
        <ContactInfo>
          <Name Type="">
            <Prefix/>
            <LastName/>
            <FirstName/>
            <MiddleName/>
            <Suffix/>
            <PreferredName/>
            <SortName/>
            <FullName/>
          </Name>
          <PositionTitle/>
          <Role/>
          <Address Type="" TypeCodeset="">
            <Street>
              <Line1/>
              <Line2/>
              <Line3/>
              <Complex/>
              <StreetNumber/>
              <StreetPrefix/>
              <StreetName/>
              <StreetType/>
              <StreetSuffix/>
              <ApartmentType/>
              <ApartmentNumberPrefix/>
              <ApartmentNumber/>
              <ApartmentNumberSuffix/>
            </Street>
            <City/>
            <County/>
            <StateProvince Codeset=""/>
            <StateANSICode Codeset=""/>
            <Country Codeset=""/>
            <PostalCode/>
            <GridLocation>
              <Latitude/>
              <Longitude/>
            </GridLocation>
            <AddressRefId/>
          </Address>
          <AddressRefId/>
          <EmailList>
            <Email SIF_Action="" Type="" TypeCodeset=""/>
            <Email SIF_Action="" Type="" TypeCodeset=""/>
          </EmailList>
          <PhoneNumberList>
            <PhoneNumber SIF_Action="" Type="" TypeCodeset="">
              <Number/>
              <Extension/>
              <ListedStatus/>
            </PhoneNumber>
            <PhoneNumber SIF_Action="" Type="" TypeCodeset="">
              <Number/>
              <Extension/>
              <ListedStatus/>
            </PhoneNumber>
          </PhoneNumberList>
        </ContactInfo>
      </LEAContact>
    </LEAContactList>
    <PhoneNumberList>
      <PhoneNumber SIF_Action="" Type="" TypeCodeset="">
        <Number/>
        <Extension/>
        <ListedStatus/>
      </PhoneNumber>
      <PhoneNumber SIF_Action="" Type="" TypeCodeset="">
        <Number/>
        <Extension/>
        <ListedStatus/>
      </PhoneNumber>
    </PhoneNumberList>
    <AddressList>
      <Address SIF_Action="" Type="" TypeCodeset="">
        <Street>
          <Line1/>
          <Line2/>
          <Line3/>
          <Complex/>
          <StreetNumber/>
          <StreetPrefix/>
          <StreetName/>
          <StreetType/>
          <StreetSuffix/>
          <ApartmentType/>
          <ApartmentNumberPrefix/>
          <ApartmentNumber/>
          <ApartmentNumberSuffix/>
        </Street>
        <City/>
        <County/>
        <StateProvince Codeset=""/>
        <StateANSICode Codeset=""/>
        <Country Codeset=""/>
        <PostalCode/>
        <GridLocation>
          <Latitude/>
          <Longitude/>
        </GridLocation>
        <AddressRefId/>
      </Address>
      <Address SIF_Action="" Type="" TypeCodeset="">
        <Street>
          <Line1/>
          <Line2/>
          <Line3/>
          <Complex/>
          <StreetNumber/>
          <StreetPrefix/>
          <StreetName/>
          <StreetType/>
          <StreetSuffix/>
          <ApartmentType/>
          <ApartmentNumberPrefix/>
          <ApartmentNumber/>
          <ApartmentNumberSuffix/>
        </Street>
        <City/>
        <County/>
        <StateProvince Codeset=""/>
        <StateANSICode Codeset=""/>
        <Country Codeset=""/>
        <PostalCode/>
        <GridLocation>
          <Latitude/>
          <Longitude/>
        </GridLocation>
        <AddressRefId/>
      </Address>
    </AddressList>
    <AddressRefIdList>
      <AddressRefId AddressRole=""/>
      <AddressRefId AddressRole=""/>
    </AddressRefIdList>
    <IdentificationInfoList>
      <IdentificationInfo Code="" CodeCodeset=""/>
      <IdentificationInfo Code="" CodeCodeset=""/>
    </IdentificationInfoList>
    <GradeLevels>
      <GradeLevel>
        <Code Codeset=""/>
        <OtherCodeList>
          <OtherCode Codeset=""/>
          <OtherCode Codeset=""/>
        </OtherCodeList>
      </GradeLevel>
      <GradeLevel>
        <Code Codeset=""/>
        <OtherCodeList>
          <OtherCode Codeset=""/>
          <OtherCode Codeset=""/>
        </OtherCodeList>
      </GradeLevel>
    </GradeLevels>
    <OperationalStatus Codeset=""/>
    <OperationalStatusDate/>
    <CongressionalDistrict/>
    <RegionOrganizationList>
      <RegionOrganization>
        <Indicator/>
        <Type/>
      </RegionOrganization>
      <RegionOrganization>
        <Indicator/>
        <Type/>
      </RegionOrganization>
    </RegionOrganizationList>
    <TitleIProgramType Codeset=""/>
    <TitleIIILanguageInstructionProgramType Codeset=""/>
    <SIF_Metadata>
      <TimeElements>
        <TimeElement>
          <Type/>
          <Code/>
          <Name/>
          <Value/>
          <StartDateTime/>
          <EndDateTime/>
          <SpanGaps>
            <SpanGap>
              <Type/>
              <Code/>
              <Name/>
              <Value/>
              <StartDateTime/>
              <EndDateTime/>
            </SpanGap>
            <SpanGap>
              <Type/>
              <Code/>
              <Name/>
              <Value/>
              <StartDateTime/>
              <EndDateTime/>
            </SpanGap>
          </SpanGaps>
          <IsCurrent/>
        </TimeElement>
        <TimeElement>
          <Type/>
          <Code/>
          <Name/>
          <Value/>
          <StartDateTime/>
          <EndDateTime/>
          <SpanGaps>
            <SpanGap>
              <Type/>
              <Code/>
              <Name/>
              <Value/>
              <StartDateTime/>
              <EndDateTime/>
            </SpanGap>
            <SpanGap>
              <Type/>
              <Code/>
              <Name/>
              <Value/>
              <StartDateTime/>
              <EndDateTime/>
            </SpanGap>
          </SpanGaps>
          <IsCurrent/>
        </TimeElement>
      </TimeElements>
      <LifeCycle>
        <Created>
          <DateTime/>
          <Creators>
            <Creator>
              <Name/>
              <ID/>
            </Creator>
            <Creator>
              <Name/>
              <ID/>
            </Creator>
          </Creators>
        </Created>
        <ModificationHistory>
          <Modified>
            <By/>
            <DateTime/>
            <Description/>
          </Modified>
          <Modified>
            <By/>
            <DateTime/>
            <Description/>
          </Modified>
        </ModificationHistory>
        <TimeElements>
          <TimeElement>
            <Type/>
            <Code/>
            <Name/>
            <Value/>
            <StartDateTime/>
            <EndDateTime/>
            <SpanGaps>
              <SpanGap>
                <Type/>
                <Code/>
                <Name/>
                <Value/>
                <StartDateTime/>
                <EndDateTime/>
              </SpanGap>
              <SpanGap>
                <Type/>
                <Code/>
                <Name/>
                <Value/>
                <StartDateTime/>
                <EndDateTime/>
              </SpanGap>
            </SpanGaps>
            <IsCurrent/>
          </TimeElement>
          <TimeElement>
            <Type/>
            <Code/>
            <Name/>
            <Value/>
            <StartDateTime/>
            <EndDateTime/>
            <SpanGaps>
              <SpanGap>
                <Type/>
                <Code/>
                <Name/>
                <Value/>
                <StartDateTime/>
                <EndDateTime/>
              </SpanGap>
              <SpanGap>
                <Type/>
                <Code/>
                <Name/>
                <Value/>
                <StartDateTime/>
                <EndDateTime/>
              </SpanGap>
            </SpanGaps>
            <IsCurrent/>
          </TimeElement>
        </TimeElements>
      </LifeCycle>
      <RightsElements>
        <RightsElement>
          <Cost/>
          <FeesForUse>
            <FeeForUse>
              <UseType/>
              <MeteringType/>
              <MeteringURL/>
              <PerUseCharge Currency="" CurrencyCodeset=""/>
            </FeeForUse>
            <FeeForUse>
              <UseType/>
              <MeteringType/>
              <MeteringURL/>
              <PerUseCharge Currency="" CurrencyCodeset=""/>
            </FeeForUse>
          </FeesForUse>
          <CopyrightStatement/>
          <TermsOfUse/>
        </RightsElement>
        <RightsElement>
          <Cost/>
          <FeesForUse>
            <FeeForUse>
              <UseType/>
              <MeteringType/>
              <MeteringURL/>
              <PerUseCharge Currency="" CurrencyCodeset=""/>
            </FeeForUse>
            <FeeForUse>
              <UseType/>
              <MeteringType/>
              <MeteringURL/>
              <PerUseCharge Currency="" CurrencyCodeset=""/>
            </FeeForUse>
          </FeesForUse>
          <CopyrightStatement/>
          <TermsOfUse/>
        </RightsElement>
      </RightsElements>
      <EducationFilter>
        <MediaTypes>
          <MediaType/>
          <MediaType/>
        </MediaTypes>
        <GradeLevels>
          <GradeLevel>
            <Code Codeset=""/>
            <OtherCodeList>
              <OtherCode Codeset=""/>
              <OtherCode Codeset=""/>
            </OtherCodeList>
          </GradeLevel>
          <GradeLevel>
            <Code Codeset=""/>
            <OtherCodeList>
              <OtherCode Codeset=""/>
              <OtherCode Codeset=""/>
            </OtherCodeList>
          </GradeLevel>
        </GradeLevels>
        <SubjectAreas>
          <SubjectArea>
            <Code Codeset=""/>
            <OtherCodeList>
              <OtherCode Codeset=""/>
              <OtherCode Codeset=""/>
            </OtherCodeList>
          </SubjectArea>
          <SubjectArea>
            <Code Codeset=""/>
            <OtherCodeList>
              <OtherCode Codeset=""/>
              <OtherCode Codeset=""/>
            </OtherCodeList>
          </SubjectArea>
        </SubjectAreas>
        <InterestLevels>
          <InterestLevel>
            <Code Codeset=""/>
            <OtherCodeList>
              <OtherCode Codeset=""/>
              <OtherCode Codeset=""/>
            </OtherCodeList>
          </InterestLevel>
          <InterestLevel>
            <Code Codeset=""/>
            <OtherCodeList>
              <OtherCode Codeset=""/>
              <OtherCode Codeset=""/>
            </OtherCodeList>
          </InterestLevel>
        </InterestLevels>
        <LearningStandardItems>
          <LearningStandardItemRefId/>
          <LearningStandardItemRefId/>
        </LearningStandardItems>
        <BloomsTaxonomyLevels>
          <BloomsTaxonomyLevel Codeset=""/>
          <BloomsTaxonomyLevel Codeset=""/>
        </BloomsTaxonomyLevels>
        <MultipleIntelligences>
          <MultipleIntelligence Codeset=""/>
          <MultipleIntelligence Codeset=""/>
        </MultipleIntelligences>
        <InstructionalStrategies>
          <InstructionalStrategy Codeset=""/>
          <InstructionalStrategy Codeset=""/>
        </InstructionalStrategies>
        <Title/>
        <Summary/>
        <LearningObjectives>
          <LearningObjective/>
          <LearningObjective/>
        </LearningObjectives>
        <ResourceTypes>
          <ResourceType Codeset=""/>
          <ResourceType Codeset=""/>
        </ResourceTypes>
      </EducationFilter>
    </SIF_Metadata>
    <SIF_ExtendedElements>
      <SIF_ExtendedElement Name="" SIF_Action=""/>
      <SIF_ExtendedElement Name="" SIF_Action=""/>
    </SIF_ExtendedElements>
  </LEAInfo>
</LEAInfos>
